ps/__init__.py
ps/base.py
ps/raw.py
ps/util.py
ps-0.0.6.dist-info/LICENSE
ps-0.0.6.dist-info/METADATA
ps-0.0.6.dist-info/WHEEL
ps-0.0.6.dist-info/top_level.txt
ps-0.0.6.dist-info/RECORD
