Metadata-Version: 2.1
Name: ps
Version: 0.0.6
Summary: Call any available system command from python
Home-page: https://github.com/thorwhalen/ps
Author: Thor Whalen
License: apache-2.0
Platform: any
License-File: LICENSE
